setup.py
stick_slip_learn/__init__.py
stick_slip_learn.egg-info/PKG-INFO
stick_slip_learn.egg-info/SOURCES.txt
stick_slip_learn.egg-info/dependency_links.txt
stick_slip_learn.egg-info/not-zip-safe
stick_slip_learn.egg-info/top_level.txt