Metadata-Version: 1.0
Name: stick-slip-learn
Version: 0.1
Summary: Training algorithms to predict stick and slip in granular avalanches
Home-page: http://github.com/lenkatilka/stick_slip_learn
Author: Lenka Kovalcinova
Author-email: lenka.kovalcinova@gmail.com
License: MIT
Platform: UNKNOWN
